ordpy/__init__.py
ordpy/ordpy.py
ordpy-1.2.0.dist-info/licenses/LICENSE
ordpy-1.2.0.dist-info/METADATA
ordpy-1.2.0.dist-info/WHEEL
ordpy-1.2.0.dist-info/top_level.txt
ordpy-1.2.0.dist-info/RECORD
