Metadata-Version: 2.4
Name: ordpy
Version: 1.2.0
Summary: A Python package for data analysis with permutation entropy and ordinal network methods
Home-page: https://github.com/arthurpessa/ordpy
Author: Arthur A. B. Pessa and Haroldo V. Ribeiro
Author-email: "Arthur A. B. Pessa and Haroldo V. Ribeiro" <arthur_pessa@hotmail.com>
Project-URL: Homepage, https://github.com/arthurpessa/ordpy
Project-URL: Repository, https://github.com/arthurpessa/ordpy
Project-URL: Issues, https://github.com/arthurpessa/ordpy/issues
Classifier: Programming Language :: Python :: 3
Classifier: License :: OSI Approved :: MIT License
Classifier: Operating System :: OS Independent
Requires-Python: >=3.6
License-File: LICENSE
Dynamic: author
Dynamic: home-page
Dynamic: license-file
Dynamic: requires-python
